altinity_datasets/__init__.py
altinity_datasets/ad_cli.py
altinity_datasets/api.py
altinity_datasets/clickhouse.py
altinity_datasets/proc_pool.py
altinity_datasets/built-ins/iris/manifest.yaml
altinity_datasets/built-ins/iris/data/iris/iris.csv
altinity_datasets/built-ins/iris/ddl/iris.sql
altinity_datasets/built-ins/weather/manifest.yaml
altinity_datasets/built-ins/weather/data/central_park_weather_observations/data-201601.csv
altinity_datasets/built-ins/weather/data/central_park_weather_observations/data-201602.csv
altinity_datasets/built-ins/weather/data/central_park_weather_observations/data-201603.csv
altinity_datasets/built-ins/weather/data/central_park_weather_observations/data-201604.csv
altinity_datasets/built-ins/weather/data/central_park_weather_observations/data-201605.csv
altinity_datasets/built-ins/weather/data/central_park_weather_observations/data-201606.csv
altinity_datasets/built-ins/weather/data/central_park_weather_observations/data-201607.csv
altinity_datasets/built-ins/weather/data/central_park_weather_observations/data-201608.csv
altinity_datasets/built-ins/weather/data/central_park_weather_observations/data-201609.csv
altinity_datasets/built-ins/weather/data/central_park_weather_observations/data-201610.csv
altinity_datasets/built-ins/weather/data/central_park_weather_observations/data-201611.csv
altinity_datasets/built-ins/weather/data/central_park_weather_observations/data-201612.csv
altinity_datasets/built-ins/weather/ddl/central_park_weather_observations.sql
altinity_datasets/built-ins/wine/manifest.yaml
altinity_datasets/built-ins/wine/data/wine/wine.csv.gz
altinity_datasets/built-ins/wine/ddl/wine.sql
altinity_datasets-0.1.1.dist-info/LICENSE
altinity_datasets-0.1.1.dist-info/METADATA
altinity_datasets-0.1.1.dist-info/WHEEL
altinity_datasets-0.1.1.dist-info/entry_points.txt
altinity_datasets-0.1.1.dist-info/top_level.txt
altinity_datasets-0.1.1.dist-info/RECORD
