Metadata-Version: 2.1
Name: altinity-datasets
Version: 0.1.1
Summary: Altinity Datasets for ClickHouse
Home-page: https://github.com/Altinity/altinity-datasets
Author: R Hodges
Author-email: info@altinity.com
License: Apache 2.0
Platform: UNKNOWN
Classifier: Programming Language :: Python :: 3
Classifier: License :: OSI Approved :: Apache Software License
Classifier: Operating System :: OS Independent
Classifier: Intended Audience :: Developers
Classifier: Intended Audience :: System Administrators
Requires-Dist: click (>=6.7)
Requires-Dist: clickhouse-driver (>=0.0.18)
Requires-Dist: PyYAML (>=3.13)
